json2unique/__init__.py
json2unique/__main__.py
json2unique/context_manager.py
json2unique/parser.py
json2unique-1.0.0.dist-info/LICENSE
json2unique-1.0.0.dist-info/METADATA
json2unique-1.0.0.dist-info/WHEEL
json2unique-1.0.0.dist-info/entry_points.txt
json2unique-1.0.0.dist-info/top_level.txt
json2unique-1.0.0.dist-info/RECORD
