Metadata-Version: 2.1
Name: json2unique
Version: 1.0.0
Summary: Parses the json document into a list of unique elements
Author: Vlad Gavrilov
License: MIT License        
Project-URL: Homepage, https://github.com/vlad-gavrilov/json2unique
Project-URL: Bug Tracker, https://github.com/vlad-gavrilov/json2unique/issues
Keywords: json,parser,cli
Classifier: License :: OSI Approved :: MIT License
Classifier: Programming Language :: Python
Classifier: Programming Language :: Python :: 3
Requires-Python: >=3.8
License-File: LICENSE
Provides-Extra: build
Requires-Dist: build ; extra == 'build'
Requires-Dist: twine ; extra == 'build'
Provides-Extra: dev
Requires-Dist: pytest ; extra == 'dev'
